mkp/__init__.py
mkp/_version.py
mkp/cli/__init__.py
mkp/cli/extract.py
mkp/cli/init.py
mkp-0.7.dist-info/licenses/LICENSE
mkp-0.7.dist-info/METADATA
mkp-0.7.dist-info/WHEEL
mkp-0.7.dist-info/entry_points.txt
mkp-0.7.dist-info/top_level.txt
mkp-0.7.dist-info/RECORD
